{"remainingRequest":"D:\\xjs\\workProject\\hwparent\\node_modules\\vue-loader\\lib\\index.js??vue-loader-options!D:\\xjs\\workProject\\hwparent\\app\\js\\money\\adc.vue?vue&type=script&lang=js&","dependencies":[{"path":"D:\\xjs\\workProject\\hwparent\\app\\js\\money\\adc.vue","mtime":1544011058000},{"path":"D:\\xjs\\workProject\\hwparent\\node_modules\\cache-loader\\dist\\cjs.js","mtime":1544689243120},{"path":"D:\\xjs\\workProject\\hwparent\\node_modules\\vue-loader\\lib\\index.js","mtime":1544689245114}],"contextDependencies":[],"result":["//\n//\n//\n//\n//\n//\n//\n//\n\r\nimport Panel from \"../core/panel.vue\"\r\nexport default {\r\n    components: {\r\n        Panel,\r\n    }\r\n}\r\n",{"version":3,"sources":["adc.vue"],"names":[],"mappings":";;;;;;;;;AASA;AACA;AACA;AACA;AACA;AACA","file":"adc.vue","sourceRoot":"app\\js\\money","sourcesContent":["<template>\r\n    <Panel title=\"京东智投\" :class=\"$style.panel\">\r\n        <section :class=\"$style.content\">\r\n            <img src=\"//img12.360buyimg.com/jrpmobile/jfs/t7162/219/4755741/18941/4e51a5aa/597b066dNf6c7a972.jpg?width=750&height=120\" alt=\"\">\r\n        </section>\r\n    </Panel>\r\n</template>\r\n\r\n<script>\r\nimport Panel from \"../core/panel.vue\"\r\nexport default {\r\n    components: {\r\n        Panel,\r\n    }\r\n}\r\n</script>\r\n<style lang=\"scss\" module>\r\n  @import \"../../css/element.scss\";\r\n  .panel{\r\n    @include panel;\r\n    margin-bottom: 0;\r\n    >h4{\r\n      display: none;\r\n    }\r\n    .content{\r\n      img{\r\n        width: 100%;\r\n        height: 100%;\r\n      }\r\n    }\r\n  }\r\n</style>\r\n"]}]}